socon_embedded/__init__.py
socon_embedded/_version.py
socon_embedded/exceptions.py
socon_embedded/managers.py
socon_embedded/action/__init__.py
socon_embedded/action/call.py
socon_embedded/action/copy.py
socon_embedded/action/move.py
socon_embedded/builder/__init__.py
socon_embedded/builder/parser.py
socon_embedded/builder/result.py
socon_embedded/executor/__init__.py
socon_embedded/executor/app_executor.py
socon_embedded/executor/task_executor.py
socon_embedded/executor/task_result.py
socon_embedded/management/__init__.py
socon_embedded/management/commands/__init__.py
socon_embedded/management/commands/build.py
socon_embedded/management/commands/subcommands/__init__.py
socon_embedded/management/commands/subcommands/from_file.py
socon_embedded/schema/__init__.py
socon_embedded/schema/apps.py
socon_embedded/schema/base.py
socon_embedded/schema/task.py
socon_embedded/utils/__init__.py
socon_embedded/utils/converter.py
socon_embedded/utils/jinja.py
socon_embedded/utils/loader.py
socon_embedded/utils/parser.py
socon_embedded-0.1a5.dist-info/AUTHORS
socon_embedded-0.1a5.dist-info/LICENSE
socon_embedded-0.1a5.dist-info/METADATA
socon_embedded-0.1a5.dist-info/WHEEL
socon_embedded-0.1a5.dist-info/top_level.txt
socon_embedded-0.1a5.dist-info/RECORD
