Metadata-Version: 2.1
Name: socon-embedded
Version: 0.1a5
Summary: Build/Flash tool plugin for socon
Author-email: Stephane Capponi <stephane.capponi@proton.me>
License: BSD-3-Clause
Project-URL: repository, https://github.com/socon-dev/socon-embedded
Keywords: build,flasH,embedded,socon
Classifier: Intended Audience :: Developers
Classifier: License :: OSI Approved :: BSD License
Classifier: Operating System :: OS Independent
Classifier: Programming Language :: Python
Classifier: Programming Language :: Python :: 3
Classifier: Programming Language :: Python :: 3 :: Only
Classifier: Programming Language :: Python :: 3.9
Classifier: Topic :: Software Development :: Libraries :: Application Frameworks
Classifier: Topic :: Software Development :: Libraries :: Python Modules
Requires-Python: >=3.9
License-File: LICENSE
License-File: AUTHORS
Requires-Dist: PyYAML ==6.0
Requires-Dist: Jinja2 ==3.1.2
Requires-Dist: datalookup ==1.0.1
Requires-Dist: pydantic ==2.5.3
Requires-Dist: socon ==0.2.1
Requires-Dist: junitparser ==3.1.0
